LICENSE
MANIFEST.in
README.md
setup.py
atomicapp_builder/__init__.py
atomicapp_builder/builder.py
atomicapp_builder/cli.py
atomicapp_builder/constants.py
atomicapp_builder/docker_registry.py
atomicapp_builder/exceptions.py
atomicapp_builder/resolver.py
atomicapp_builder.egg-info/PKG-INFO
atomicapp_builder.egg-info/SOURCES.txt
atomicapp_builder.egg-info/dependency_links.txt
atomicapp_builder.egg-info/entry_points.txt
atomicapp_builder.egg-info/requires.txt
atomicapp_builder.egg-info/top_level.txt
test/__init__.py
test/constants.py
test/test_resolver.py
test/util.py