Metadata-Version: 1.1
Name: atomicapp-builder
Version: 0.0.1
Summary: Application for building Atomicapps
Home-page: UNKNOWN
Author: Slavek Kabrda
Author-email: slavek@redhat.com
License: BSD
Keywords: atomic,atomicapp,docker,nulecule
Platform: UNKNOWN
Classifier: Development Status :: 3 - Alpha
Classifier: Intended Audience :: Developers
Classifier: Intended Audience :: System Administrators
Classifier: License :: OSI Approved :: BSD License
Classifier: Operating System :: POSIX :: Linux
Classifier: Programming Language :: Python
